README.txt
setup.cfg
setup.py
docs/HISTORY.txt
docs/LICENSE
iw/__init__.py
iw.memberreplace.egg-info/PKG-INFO
iw.memberreplace.egg-info/SOURCES.txt
iw.memberreplace.egg-info/dependency_links.txt
iw.memberreplace.egg-info/entry_points.txt
iw.memberreplace.egg-info/namespace_packages.txt
iw.memberreplace.egg-info/not-zip-safe
iw.memberreplace.egg-info/requires.txt
iw.memberreplace.egg-info/top_level.txt
iw/memberreplace/__init__.py
iw/memberreplace/config.py
iw/memberreplace/configure.zcml
iw/memberreplace/utils.py
iw/memberreplace/browser/__init__.py
iw/memberreplace/browser/controlpanel.py
iw/memberreplace/locales/README.txt
iw/memberreplace/locales/iw.memberreplace.pot
iw/memberreplace/locales/updatelocales.py
iw/memberreplace/locales/fr/LC_MESSAGES/iw.memberreplace.mo
iw/memberreplace/locales/fr/LC_MESSAGES/iw.memberreplace.po
iw/memberreplace/profiles/default/actionicons.xml
iw/memberreplace/profiles/default/controlpanel.xml
iw/memberreplace/profiles/default/metadata.xml
iw/memberreplace/tests/README.txt
iw/memberreplace/tests/__init__.py
iw/memberreplace/tests/base.py
iw/memberreplace/tests/test_controlpanel.txt
iw/memberreplace/tests/test_functional.py