Metadata-Version: 1.0
Name: iw.memberreplace
Version: 1.0.0alpha1
Summary: Replace a Plone member by another one (ownership, creators, sharings and mutable groups).
Home-page: http://plone.org/products/iw.memberreplace
Author: Ingeniweb
Author-email: support@ingeniweb.com
License: GPL
Keywords: plone membership
Platform: UNKNOWN
Classifier: Framework :: Plone
Classifier: Programming Language :: Python
Classifier: Topic :: Software Development :: Libraries :: Python Modules
